touch_callable/__init__.py
touch_callable/requirements.txt
touch_callable/touch_callable.py
touch_callable/front-end/build/asset-manifest.json
touch_callable/front-end/build/favicon.ico
touch_callable/front-end/build/index.html
touch_callable/front-end/build/logo192.png
touch_callable/front-end/build/logo512.png
touch_callable/front-end/build/manifest.json
touch_callable/front-end/build/precache-manifest.bf65c13fcc62cf82c115103879d5219c.js
touch_callable/front-end/build/robots.txt
touch_callable/front-end/build/service-worker.js
touch_callable/front-end/build/static/css/2.aa7fcd32.chunk.css
touch_callable/front-end/build/static/css/2.aa7fcd32.chunk.css.map
touch_callable/front-end/build/static/css/main.6e6e8990.chunk.css
touch_callable/front-end/build/static/css/main.6e6e8990.chunk.css.map
touch_callable/front-end/build/static/js/2.06c9250b.chunk.js
touch_callable/front-end/build/static/js/2.06c9250b.chunk.js.map
touch_callable/front-end/build/static/js/main.174d5a92.chunk.js
touch_callable/front-end/build/static/js/main.174d5a92.chunk.js.map
touch_callable/front-end/build/static/js/runtime~main.e543b2a5.js
touch_callable/front-end/build/static/js/runtime~main.e543b2a5.js.map
touch_callable/front-end/build/static/media/logo.3dedce73.svg
touch_callable/front-end/build/static/media/touch-callable-text.edef1c3c.svg
touch_callable-0.1.0.dist-info/LICENSE
touch_callable-0.1.0.dist-info/METADATA
touch_callable-0.1.0.dist-info/WHEEL
touch_callable-0.1.0.dist-info/entry_points.txt
touch_callable-0.1.0.dist-info/top_level.txt
touch_callable-0.1.0.dist-info/RECORD
