Metadata-Version: 2.1
Name: touch-callable
Version: 0.1.0
Summary: Automatically generate a Web UI for Python function using type annotations.
Home-page: https://github.com/pengwk/touch-callable
Author: Peng Weikang
Author-email: pengwk@pengwk.com
License: UNKNOWN
Platform: UNKNOWN
Classifier: Programming Language :: Python :: 3
Classifier: License :: OSI Approved :: MIT License
Classifier: Operating System :: OS Independent
Requires-Python: >=3.6
Requires-Dist: Flask
Requires-Dist: pytz
